custom_base_django/__init__.py
custom_base_django/_tests.py
custom_base_django/admin.py
custom_base_django/apps.py
custom_base_django/language_utils.py
custom_base_django/local_user.py
custom_base_django/managers.py
custom_base_django/middleware.py
custom_base_django/signals.py
custom_base_django/tasks.py
custom_base_django/urls.py
custom_base_django/utils.py
custom_base_django/_utils/google_sheet.py
custom_base_django/_utils/json_tools.py
custom_base_django/_utils/url_based.py
custom_base_django/functions/__init__.py
custom_base_django/functions/function_registry.py
custom_base_django/functions/permissions.py
custom_base_django/functions/tests.py
custom_base_django/functions/views.py
custom_base_django/management/__init__.py
custom_base_django/management/commands/__init__.py
custom_base_django/management/commands/generate_data.py
custom_base_django/management/commands/load_data.py
custom_base_django/migrations/0001_initial.py
custom_base_django/migrations/__init__.py
custom_base_django/models/__init__.py
custom_base_django/models/base.py
custom_base_django/models/choices.py
custom_base_django/models/custom_fields.py
custom_base_django/models/periodict_tasks.py
custom_base_django/models/workflow.py
custom_base_django/serializers/__init__.py
custom_base_django/serializers/base.py
custom_base_django/serializers/custom_fields.py
custom_base_django/serializers/state_serializer.py
custom_base_django/serializers/workflow_serializer.py
custom_base_django/tests/test_api.py
custom_base_django/views/__init__.py
custom_base_django/views/base_views.py
custom_base_django/views/workflow_views.py
custom_base_django-0.1.9.dist-info/licenses/licence.lic
custom_base_django-0.1.9.dist-info/METADATA
custom_base_django-0.1.9.dist-info/WHEEL
custom_base_django-0.1.9.dist-info/top_level.txt
custom_base_django-0.1.9.dist-info/RECORD
