Metadata-Version: 2.4
Name: custom-base-django
Version: 0.1.9
Summary: A customizable Django base package with DRF, JWT, Persian support, and Elasticsearch integration.
Author-email: Ali Haji Nezhad <ali.hajinezhad@email.com>
Project-URL: Homepage, https://github.com/yourusername/custom-base-django
Project-URL: Source, https://github.com/yourusername/custom-base-django
Project-URL: BugTracker, https://github.com/yourusername/custom-base-django/issues
Classifier: Framework :: Django
Classifier: Framework :: Django :: 4
Classifier: Programming Language :: Python
Classifier: Programming Language :: Python :: 3
Classifier: Programming Language :: Python :: 3.8
Classifier: Operating System :: OS Independent
Requires-Python: >=3.8
License-File: licence.lic
Requires-Dist: Django>=4.2
Requires-Dist: djangorestframework
Requires-Dist: djangorestframework-simplejwt
Requires-Dist: jdatetime
Requires-Dist: elasticsearch_dsl
Requires-Dist: aiohttp
Dynamic: license-file
